<item>
	<title>Episode 01 - Stewie's First Word</title>
	<link>
	<sublink>https://qd6qsuqis6edd5gp192vgccnw.rklar3sbo0cqzmbfsk2zoqmdizf.xyz/TV%20Series/Family%20Guy%201999/S19/WEBRip%20720p%20x265/Family.Guy.S19E01.720p.WEBRip.2CH.x265.HEVC.PSA.mkv</sublink>
	</link>
	<thumbnail>https://m.media-amazon.com/images/M/MV5BYzViMWIxZTYtNzZkZi00YTEwLTk5MzMtYjQ1ODVlN2VkZjc1XkEyXkFqcGdeQXVyMjYwNDA2MDE@._V1_FMjpg_UX600_.jpg</thumbnail>
</item>

<item>
	<title>Episode 02 - The Talented Mr. Stewie</title>
	<link>
	<sublink>https://qd6qsuqis6edd5gp192vgccnw.rklar3sbo0cqzmbfsk2zoqmdizf.xyz/TV%20Series/Family%20Guy%201999/S19/WEBRip%20720p%20x265/Family.Guy.S19E02.720p.WEBRip.2CH.x265.HEVC.PSA.mkv</sublink>
	</link>
	<thumbnail>https://m.media-amazon.com/images/M/MV5BMDlhZDExYWUtNzEzYy00YTMyLWFkODQtNGNlOTMyMjhkM2U5XkEyXkFqcGdeQXVyMjYwNDA2MDE@._V1_FMjpg_UX600_.jpg</thumbnail>
</item>

<item>
	<title>Episode 03 - Boys & Squirrels</title>
	<link>
	<sublink>https://qd6qsuqis6edd5gp192vgccnw.rklar3sbo0cqzmbfsk2zoqmdizf.xyz/TV%20Series/Family%20Guy%201999/S19/WEBRip%20720p%20x265/Family.Guy.S19E03.720p.WEBRip.2CH.x265.HEVC.PSA.mkv</sublink>
	</link>
	<thumbnail>https://m.media-amazon.com/images/M/MV5BNjQ1ODE1ZjMtYTVhNi00M2Q2LTg0ZTctZDdhNmY4ZDMzZWQyXkEyXkFqcGdeQXVyMjYwNDA2MDE@._V1_FMjpg_UX600_.jpg</thumbnail>
</item>

<item>
	<title>Episode 04 - CutawayLand</title>
	<link>
	<sublink>https://qd6qsuqis6edd5gp192vgccnw.rklar3sbo0cqzmbfsk2zoqmdizf.xyz/TV%20Series/Family%20Guy%201999/S19/WEBRip%20720p%20x265/Family.Guy.S19E04.720p.WEBRip.2CH.x265.HEVC.PSA.mkv</sublink>
	</link>
	<thumbnail>https://m.media-amazon.com/images/M/MV5BYmFjODE2YjQtMjNmMS00NzBmLWEyNTQtNjMwZWI4MGJmOGYzXkEyXkFqcGdeQXVyODUzODkwNDQ@._V1_FMjpg_UX600_.jpg</thumbnail>
</item>

<item>
	<title>Episode 05 - La Famiglia Guy</title>
	<link>
	<sublink>https://qd6qsuqis6edd5gp192vgccnw.rklar3sbo0cqzmbfsk2zoqmdizf.xyz/TV%20Series/Family%20Guy%201999/S19/WEBRip%20720p%20x265/Family.Guy.S19E05.720p.WEBRip.2CH.x265.HEVC.PSA.mkv</sublink>
	</link>
	<thumbnail>https://m.media-amazon.com/images/M/MV5BZjhkNmIwNTYtZjI5NS00OGE3LThlZjYtYmQ0NTEwZTU4ZmQ3XkEyXkFqcGdeQXVyMjYwNDA2MDE@._V1_FMjpg_UX600_.jpg</thumbnail>
</item>

<item>
	<title>Episode 06 - Meg's Wedding</title>
	<link>
	<sublink>https://qd6qsuqis6edd5gp192vgccnw.rklar3sbo0cqzmbfsk2zoqmdizf.xyz/TV%20Series/Family%20Guy%201999/S19/WEBRip%20720p%20x265/Family.Guy.S19E06.720p.WEBRip.2CH.x265.HEVC.PSA.mkv</sublink>
	</link>
	<thumbnail>https://m.media-amazon.com/images/M/MV5BNmYxOWE2NjktNDkyMS00OGI4LTg3ZjEtOWYzYmMwNTBmYTcyXkEyXkFqcGdeQXVyMjYwNDA2MDE@._V1_FMjpg_UX600_.jpg</thumbnail>
</item>

<item>
	<title>Episode 07 - Wild Wild West</title>
	<link>
	<sublink>https://qd6qsuqis6edd5gp192vgccnw.rklar3sbo0cqzmbfsk2zoqmdizf.xyz/TV%20Series/Family%20Guy%201999/S19/WEBRip%20720p%20x265/Family.Guy.S19E07.720p.WEBRip.2CH.x265.HEVC.PSA.mkv</sublink>
	</link>
	<thumbnail>https://m.media-amazon.com/images/M/MV5BOGI2ODgyYzEtNjMyZS00YWI4LWJiODgtNzQwNjI2YzJiMGU1XkEyXkFqcGdeQXVyMjYwNDA2MDE@._V1_FMjpg_UX600_.jpg</thumbnail>
</item>

<item>
	<title>Episode 08 - Pawtucket Pat</title>
	<link>
	<sublink>https://qd6qsuqis6edd5gp192vgccnw.rklar3sbo0cqzmbfsk2zoqmdizf.xyz/TV%20Series/Family%20Guy%201999/S19/WEBRip%20720p%20x265/Family.Guy.S19E08.720p.WEBRip.2CH.x265.HEVC.PSA.mkv</sublink>
	</link>
	<thumbnail>https://m.media-amazon.com/images/M/MV5BMjlkOTYzNDktODg4OS00MmZlLWExNzctZmFjNDk3Zjg0MWVjXkEyXkFqcGdeQXVyMjYwNDA2MDE@._V1_FMjpg_UX600_.jpg</thumbnail>
</item>

<item>
	<title>Episode 09 - The First No L</title>
 <meta>
	<content>episode</content>
	<imdb>tt13502598</imdb>
	<tvshowtitle>Family Guy</tvshowtitle>
	<year>1999</year>
	<title>The First No L</title>
	<premiered>December 13, 2020</premiered>
	<season>19</season>
	<episode>9</episode>
 </meta>
	<link>
	<sublink>https://qd6qsuqis6edd5gp192vgccnw.rklar3sbo0cqzmbfsk2zoqmdizf.xyz/TV%20Series/Family%20Guy%201999/S19/WEBRip%20720p%20x265/Family.Guy.S19E09.720p.WEBRip.2CH.x265.HEVC.PSA.mkv</sublink>
	</link>
	<thumbnail>https://m.media-amazon.com/images/M/MV5BOWJmNmRlZjItYjExZC00YjE3LWI3YTktNDBlZWFmYzgzYmUxXkEyXkFqcGdeQXVyMTIwODMyNjIw._V1_FMjpg_UX600_.jpg</thumbnail>
</item>

<item>
	<title>Episode 10 - Fecal Matters</title>
	<link>
	<sublink>https://qd6qsuqis6edd5gp192vgccnw.rklar3sbo0cqzmbfsk2zoqmdizf.xyz/TV%20Series/Family%20Guy%201999/S19/WEBRip%20720p%20x265/Family.Guy.S19E10.720p.WEBRip.2CH.x265.HEVC.PSA.mkv</sublink>
	</link>
	<thumbnail>https://m.media-amazon.com/images/M/MV5BMjczOGRjODktMWM0NS00YjgyLTk3N2UtMjEyZDgwNzlmNWYzXkEyXkFqcGdeQXVyMjYwNDA2MDE@._V1_FMjpg_UX1280_.jpg</thumbnail>
</item>

<item>
	<title>19x11 Boy’s Best Friend</title>
	<link>
	<sublink>https://qd6qsuqis6edd5gp192vgccnw.rklar3sbo0cqzmbfsk2zoqmdizf.xyz/TV%20Series/Family%20Guy%201999/S19/WEBRip%20720p%20x265/Family.Guy.S19E11.720p.WEBRip.2CH.x265.HEVC.PSA.mkv</sublink>
	</link>
	<thumbnail>https://walter.trakt.tv/images/shows/000/001/425/fanarts/thumb/acc8c9aff4.jpg.webp</thumbnail>
</item>

<item>
	<title>19x12 And Then There's Fraud</title>
	<link>
	<sublink>https://qd6qsuqis6edd5gp192vgccnw.rklar3sbo0cqzmbfsk2zoqmdizf.xyz/TV%20Series/Family%20Guy%201999/S19/WEBRip%20720p%20x265/Family.Guy.S19E12.720p.WEBRip.2CH.x265.HEVC.PSA.mkv</sublink>
	</link>
	<thumbnail>https://trakt.tv/shows/family-guy/seasons/19/episodes/12</thumbnail>
</item>

<item>
	<title>19x13 PeTerminator</title>
	<link>
	<sublink>https://qd6qsuqis6edd5gp192vgccnw.rklar3sbo0cqzmbfsk2zoqmdizf.xyz/TV%20Series/Family%20Guy%201999/S19/WEBRip%20720p%20x265/Family.Guy.S19E13.720p.WEBRip.2CH.x265.HEVC.PSA.mkv</sublink>
	</link>
</item>

<item>
	<title>19x14 The Marrying Kind</title>
	<link>
	<sublink>https://qd6qsuqis6edd5gp192vgccnw.rklar3sbo0cqzmbfsk2zoqmdizf.xyz/TV%20Series/Family%20Guy%201999/S19/WEBRip%20720p%20x265/Family.Guy.S19E14.720p.WEBRip.2CH.x265.HEVC.PSA.mkv</sublink>
	</link>
</item>

<item>
	<title>19x15 Customer of the Week</title>
	<link>
	<sublink>https://qd6qsuqis6edd5gp192vgccnw.rklar3sbo0cqzmbfsk2zoqmdizf.xyz/TV%20Series/Family%20Guy%201999/S19/WEBRip%20720p%20x265/Family.Guy.S19E15.720p.WEBRip.2CH.x265.HEVC.PSA.mkv</sublink>
	</link>
	<thumbnail>https://trakt.tv/shows/family-guy/seasons/19/episodes/12</thumbnail>
</item>

<item>
	<title>19x16 Who's Brian Now?</title>
	<link>
	<sublink>https://qd6qsuqis6edd5gp192vgccnw.rklar3sbo0cqzmbfsk2zoqmdizf.xyz/TV%20Series/Family%20Guy%201999/S19/WEBRip%20720p%20x265/Family.Guy.S19E16.720p.WEBRip.2CH.x265.HEVC.PSA.mkv</sublink>
	</link>
</item>

<item>
	<title>19x17 Young Parent Trap</title>
	<link>
	<sublink>https://qd6qsuqis6edd5gp192vgccnw.rklar3sbo0cqzmbfsk2zoqmdizf.xyz/TV%20Series/Family%20Guy%201999/S19/WEBRip%20720p%20x265/Family.Guy.S19E17.720p.WEBRip.2CH.x265.HEVC.PSA.mkv</sublink>
	</link>
</item>